sandbox_executor/__init__.py
sandbox_executor/client.py
sandbox_executor/config.py
sandbox_executor/exceptions.py
sandbox_executor/executor.py
sandbox_executor/executors/__init__.py
sandbox_executor/executors/sandbox_executor.py
sandbox_executor/executors/secure_sandbox_executor.py
sandbox_executor-0.1.2.dist-info/licenses/LICENSE
sandbox_executor-0.1.2.dist-info/METADATA
sandbox_executor-0.1.2.dist-info/WHEEL
sandbox_executor-0.1.2.dist-info/top_level.txt
sandbox_executor-0.1.2.dist-info/RECORD
