Metadata-Version: 2.4
Name: sandbox-executor
Version: 0.1.2
Summary: A secure Python code execution sandbox
Author-email: dinhhungitsoft <dinhhungitsoft@gmail.com>
License:                                  Apache License
Project-URL: Homepage, https://github.com/dinhhungitsoft/secure-python-sandbox
Project-URL: Repository, https://github.com/dinhhungitsoft/secure-python-sandbox
Project-URL: Issues, https://github.com/dinhhungitsoft/secure-python-sandbox/issues
Keywords: sandbox,code-execution,security,python
Classifier: Development Status :: 4 - Beta
Classifier: Intended Audience :: Developers
Classifier: License :: OSI Approved :: MIT License
Classifier: Programming Language :: Python :: 3
Classifier: Programming Language :: Python :: 3.8
Classifier: Programming Language :: Python :: 3.9
Classifier: Programming Language :: Python :: 3.10
Classifier: Programming Language :: Python :: 3.11
Classifier: Programming Language :: Python :: 3.12
Classifier: Topic :: Software Development :: Libraries :: Python Modules
Classifier: Topic :: Security
Requires-Python: >=3.8
License-File: LICENSE
Requires-Dist: pydantic>=2.0.0
Requires-Dist: python-dotenv>=1.0.0
Requires-Dist: requests>=2.31.0
Provides-Extra: remote
Requires-Dist: requests>=2.31.0; extra == "remote"
Provides-Extra: api
Requires-Dist: fastapi>=0.104.0; extra == "api"
Requires-Dist: uvicorn[standard]>=0.24.0; extra == "api"
Requires-Dist: python-multipart>=0.0.6; extra == "api"
Provides-Extra: dev
Requires-Dist: pytest>=7.0.0; extra == "dev"
Requires-Dist: pytest-cov>=4.0.0; extra == "dev"
Requires-Dist: pytest-asyncio>=0.21.0; extra == "dev"
Requires-Dist: black>=23.0.0; extra == "dev"
Requires-Dist: flake8>=6.0.0; extra == "dev"
Requires-Dist: mypy>=1.0.0; extra == "dev"
Provides-Extra: all
Requires-Dist: sandbox-executor[api,dev,remote]; extra == "all"
Dynamic: license-file
